vevod_mcp/__init__.py
vevod_mcp/cli.py
vevod_mcp/mcp_server.py
vevod_mcp/api/__init__.py
vevod_mcp/api/vod.py
vevod_mcp-0.1.2.dist-info/licenses/LICENSE.txt
vevod_mcp-0.1.2.dist-info/METADATA
vevod_mcp-0.1.2.dist-info/WHEEL
vevod_mcp-0.1.2.dist-info/entry_points.txt
vevod_mcp-0.1.2.dist-info/top_level.txt
vevod_mcp-0.1.2.dist-info/RECORD
