Metadata-Version: 2.4
Name: vevod-mcp
Version: 0.1.2
Summary: VolcEngine VOD MCP
Requires-Python: >=3.11
License-File: LICENSE.txt
Requires-Dist: mcp>=1.6.0
Requires-Dist: python-dotenv>=1.1.0
Requires-Dist: volcengine>=1.0.177
Requires-Dist: starlette>=0.14.2
Requires-Dist: typing-extensions>=4.0.0
Requires-Dist: pydantic>=1.8.2
Requires-Dist: retry>=0.9.2
Dynamic: license-file
